VTT-0.3.1.dist-info/DESCRIPTION.rst
VTT-0.3.1.dist-info/METADATA
VTT-0.3.1.dist-info/RECORD
VTT-0.3.1.dist-info/WHEEL
VTT-0.3.1.dist-info/metadata.json
VTT-0.3.1.dist-info/top_level.txt
vtt/__init__.py
