Metadata-Version: 2.0
Name: VTT
Version: 0.3.1
Summary: Variable Trigonometric Threshold (VTT)
Home-page: http://github.com/rionbr/vtt
Author: Rion Brattig Correia
Author-email: rionbr@gmail.com
License: MIT
Keywords: machine learning linear model computational biology
Platform: UNKNOWN
Classifier: Development Status :: 4 - Beta
Classifier: License :: OSI Approved :: MIT License
Classifier: Programming Language :: Python :: 2.7
Classifier: Intended Audience :: Science/Research
Classifier: Topic :: Scientific/Engineering :: Information Analysis
Requires-Dist: numpy
Requires-Dist: scipy
Requires-Dist: sklearn
